{
	"Id": "0x57Cbf36788113237D64E46f25A88855c3dff1691",
	"Protocol": "d5d48ef4-7460-49d1-9d08-c682b8d85c5b",
	"Outputs": [
		{
			"Address": "0xa3fa99a148fa48d14ed51d610c367c61876997f1",
			"Apr": -9.090906,
			"GroupId": 1,
			"Key": "minimum-collateral",
			"RequiredKeyInGroup": null
		},
		{
			"Address": "0xa3fa99a148fa48d14ed51d610c367c61876997f1",
			"Apr": -25.925928,
			"GroupId": 1,
			"Key": "incentives-collateral",
			"RequiredKeyInGroup": null
		},
		{
			"Address": "0x580A84C73811E1839F75d86d75d88cCa0c241fF4",
			"Apr": 0,
			"GroupId": 0,
			"Key": "",
			"RequiredKeyInGroup": [
				{
					"Key": "incentives-collateral",
					"GroupId": 1
				}
			]
		}
	],
	"Inputs": [
		{
			"Address": "0x7d60F21072b585351dFd5E8b17109458D97ec120",
			"GroupId": 0
		}
	],
	"MinimumInputs": 0,
	"RequiredInputs": null,
	"Symbol": "Stake DAO am3CRV Strategy MAI Vault",
	"Chain": "polygon"
}